{
  "lspconfig": {
    "cssls": {
      "css.lint.unknownAtRules": "ignore",
      "less.lint.unknownAtRules": "ignore",
      "scss.lint.unknownAtRules": "ignore"
    },
    "tsserver": {
      "javascript.updateImportsOnFileMove.enabled": "always",
      "javascript.inlayHints.includeInlayParameterNameHints": "all",
      "javascript.inlayHints.includeInlayParameterNameHintsWhenArgumentMatchesName": false,
      "javascript.inlayHints.includeInlayFunctionParameterTypeHints": true,
      "javascript.inlayHints.includeInlayVariableTypeHints": true,
      "javascript.inlayHints.includeInlayVariableTypeHintsWhenTypeMatchesName": false,
      "javascript.inlayHints.includeInlayPropertyDeclarationTypeHints": true,
      "javascript.inlayHints.includeInlayFunctionLikeReturnTypeHints": true,
      "javascript.inlayHints.includeInlayEnumMemberValueHints": true,
      "typescript.updateImportsOnFileMove.enabled": "always",
      "typescript.inlayHints.includeInlayParameterNameHints": "all",
      "typescript.inlayHints.includeInlayParameterNameHintsWhenArgumentMatchesName": false,
      "typescript.inlayHints.includeInlayFunctionParameterTypeHints": true,
      "typescript.inlayHints.includeInlayVariableTypeHints": true,
      "typescript.inlayHints.includeInlayVariableTypeHintsWhenTypeMatchesName": false,
      "typescript.inlayHints.includeInlayPropertyDeclarationTypeHints": true,
      "typescript.inlayHints.includeInlayFunctionLikeReturnTypeHints": true,
      "typescript.inlayHints.includeInlayEnumMemberValueHints": true
    },
    "pylsp": {
      "pylsp.plugins.rope_autoimport.enabled": true,
      "pylsp.plugins.rope_autoimport.memory": true,
      "pylsp.plugins.rope_completion.enabled": true,
      "pylsp.plugins.rope_completion.eager": true,
      "pylsp.plugins.jedi.auto_import_modules": [
        "numpy",
        "pandas",
        "matplotlib"
      ],
      "pylsp.plugins.jedi_completion.eager": true,
      "pylsp.plugins.jedi_completion.fuzzy": true,
      "pylsp.plugins.jedi_completion.include_class_objects": true,
      "pylsp.plugins.jedi_completion.include_function_objects": true
    },
    "pyright": {
      "python.pythonPath": "python",
      "python.analysis.autoSearchPaths": true,
      "python.analysis.diagnosticMode": "workspace",
      "python.analysis.useLibraryCodeForTypes": true,
      "python.analysis.typeCheckingMode": "off"
    },
    "tailwindcss": {
      "tailwindCSS.classAttributes": [
        "class",
        "className",
        "ngClass"
      ],
      "tailwindCSS.experimental.classRegex": [
        [
          "cva\\(([^)]*)\\)",
          "[\"'`]([^\"'`]*).*?[\"'`]"
        ],
        [
          "cx\\(([^)]*)\\)",
          "(?:'|\"|`)([^']*)(?:'|\"|`)"
        ]
      ],
      "tailwindCSS.emmetCompletions": false,
      "tailwindCSS.lint.cssConflict": "warning",
      "tailwindCSS.lint.invalidApply": "error",
      "tailwindCSS.lint.invalidConfigPath": "error",
      "tailwindCSS.lint.invalidScreen": "error",
      "tailwindCSS.lint.invalidTailwindDirective": "error",
      "tailwindCSS.lint.invalidVariant": "error",
      "tailwindCSS.lint.recommendedVariantOrder": "warning",
      "tailwindCSS.validate": true
    },
    "rust_analyzer": {
      "rust-analyzer.cachePriming.enable": true,
      "rust-analyzer.cachePriming.numThreads": 0
    }
  }
}
