{
  "PWA Json manifest": {
    "prefix": "pwa-manifest",
    "description": "PWA Json Manifest",
    "types": "json",
    "body": [
      "{",
      "\"dir\": \"ltr\",",
      "\"lang\": \"en\",",
      "\"name\": \"${Name}\",",
      "\"scope\": \"/\",",
      "\"display\": \"standalone\",",
      "\"start_url\": \"./?utm_source=web_app_manifest\",",
      "\"short_name\": \"${ShortName}}\",",
      "\"theme_color\": \"#${Color}\",",
      "\"description\": \"\",",
      "\"orientation\": \"any\",",
      "\"background_color\": \"#${BackgroundColor}\",",
      "\"related_applications\": [],",
      "\"prefer_related_applications\": false,",
      "\"icons\": [",
      "\t{",
      "\t\t\"src\": \".\/assets\/${icon}-192x192.png\",",
      "\t\t\"sizes\": \"192x192\",",
      "\t\"type\": \"image/png\"",
      "\t},",
      "\t{",
      "\t\t\"src\": \".\/assets\/${icon}-512x512.png\",",
      "\t\t\"sizes\": \"512x512\",",
      "\t\t\"type\": \"image/png\"",
      "\t\t}",
      "\t]",
      "}",
      "$0"
    ]
  }
}
